htmlwithpy/__init__.py
htmlwithpy/a.py
htmlwithpy/body.py
htmlwithpy/div.py
htmlwithpy/element.py
htmlwithpy/img.py
htmlwithpy/input.py
htmlwithpy/para.py
htmlwithpy/span.py
htmlwithpy-0.0.1.dist-info/LICENSE
htmlwithpy-0.0.1.dist-info/METADATA
htmlwithpy-0.0.1.dist-info/WHEEL
htmlwithpy-0.0.1.dist-info/top_level.txt
htmlwithpy-0.0.1.dist-info/RECORD
