Metadata-Version: 2.1
Name: htmlwithpy
Version: 0.0.1
Summary: A package helps users to generate html code with python
Author-email: Sri Harsha Vandanapu <harshavandanapu1990@gmail.com>
License: Copyright (c) 2022 The Python Packaging Authority        
Classifier: Programming Language :: Python :: 3
Classifier: License :: OSI Approved :: MIT License
Classifier: Operating System :: OS Independent
Requires-Python: >=3.7
License-File: LICENSE
